{
	"generator_info": "Shape definitions generated with PhysicsEditor. Visit https://www.codeandweb.com/physicseditor",
	"ball": {
		"type": "fromPhysicsEditor",
		"label": "ball",
		"isStatic": false,
		"density": 0.2,
		"restitution": 0.1,
		"friction": 1,
		"frictionAir": 0.01,
		"frictionStatic": 0.5,
		"collisionFilter": {
			"group": 0,
			"category": 1,
			"mask": 255
		},
		"fixtures": [
			{
				"label": "",
				"isSensor": false,
				"circle": {
					"x": 34.21052631578947,
					"y": 34.63157894736841,
					"radius": 8.360651379008628
				}
			}
		]
	},
	"bounds001": {
		"type": "fromPhysicsEditor",
		"label": "bounds001",
		"isStatic": true,
		"density": 0.7999999999999999,
		"restitution": 0.1,
		"friction": 1,
		"frictionAir": 0.009999999776482582,
		"frictionStatic": 0.7,
		"collisionFilter": {
			"group": 0,
			"category": 1,
			"mask": 255
		},
		"fixtures": [
			{
				"label": "",
				"isSensor": false,
				"vertices": [
					[ { "x":292, "y":213 }, { "x":294, "y":240 }, { "x":308, "y":270 }, { "x":325, "y":287 }, { "x":405, "y":129 }, { "x":334, "y":157 }, { "x":302, "y":189 } ],
					[ { "x":913, "y":838 }, { "x":945, "y":844 }, { "x":986, "y":840 }, { "x":1024, "y":830 }, { "x":1085, "y":731 }, { "x":1076, "y":714 }, { "x":1010, "y":681 }, { "x":896, "y":824 } ],
					[ { "x":1002, "y":477 }, { "x":1011, "y":441 }, { "x":1008, "y":403 }, { "x":994, "y":368 }, { "x":948, "y":334 }, { "x":922, "y":327 }, { "x":830, "y":317 }, { "x":982, "y":503 } ],
					[ { "x":885, "y":847 }, { "x":896, "y":824 }, { "x":597, "y":930 }, { "x":714, "y":917 }, { "x":784, "y":901 }, { "x":841, "y":879 }, { "x":867, "y":864 } ],
					[ { "x":1086, "y":792 }, { "x":1093, "y":777 }, { "x":1085, "y":731 }, { "x":1024, "y":830 }, { "x":1072, "y":806 } ],
					[ { "x":763, "y":45 }, { "x":725, "y":23 }, { "x":683, "y":10 }, { "x":625, "y":1 }, { "x":564, "y":3 }, { "x":325, "y":287 }, { "x":803, "y":285 }, { "x":795, "y":78 } ],
					[ { "x":977, "y":350 }, { "x":948, "y":334 }, { "x":994, "y":368 } ],
					[ { "x":474, "y":38 }, { "x":446, "y":66 }, { "x":405, "y":129 }, { "x":325, "y":287 }, { "x":564, "y":3 }, { "x":511, "y":17 } ],
					[ { "x":896, "y":824 }, { "x":1010, "y":681 }, { "x":990, "y":656 }, { "x":0, "y":551 }, { "x":26, "y":730 }, { "x":358, "y":930 }, { "x":465, "y":934 }, { "x":597, "y":930 } ],
					[ { "x":63, "y":373 }, { "x":40, "y":404 }, { "x":21, "y":446 }, { "x":6, "y":502 }, { "x":325, "y":287 }, { "x":262, "y":288 }, { "x":174, "y":311 }, { "x":97, "y":344 } ],
					[ { "x":830, "y":208 }, { "x":826, "y":157 }, { "x":812, "y":110 }, { "x":795, "y":78 }, { "x":803, "y":285 }, { "x":824, "y":236 } ],
					[ { "x":79, "y":838 }, { "x":104, "y":862 }, { "x":153, "y":890 }, { "x":207, "y":908 }, { "x":266, "y":920 }, { "x":358, "y":930 }, { "x":26, "y":730 }, { "x":50, "y":789 } ],
					[ { "x":325, "y":287 }, { "x":6, "y":502 }, { "x":0, "y":551 }, { "x":804, "y":304 }, { "x":803, "y":285 } ],
					[ { "x":982, "y":503 }, { "x":830, "y":317 }, { "x":974, "y":525 } ],
					[ { "x":974, "y":525 }, { "x":830, "y":317 }, { "x":804, "y":304 }, { "x":970, "y":578 } ],
					[ { "x":0, "y":605 }, { "x":9, "y":668 }, { "x":26, "y":730 }, { "x":0, "y":551 } ],
					[ { "x":970, "y":578 }, { "x":804, "y":304 }, { "x":0, "y":551 }, { "x":975, "y":614 } ],
					[ { "x":990, "y":656 }, { "x":975, "y":614 }, { "x":0, "y":551 } ]
				]
			}
		]
	},
	"bounds002": {
		"type": "fromPhysicsEditor",
		"label": "bounds002",
		"isStatic": true,
		"density": 0.7999999999999999,
		"restitution": 0.1,
		"friction": 1,
		"frictionAir": 0.009999999776482582,
		"frictionStatic": 0.7,
		"collisionFilter": {
			"group": 0,
			"category": 1,
			"mask": 255
		},
		"fixtures": [
			{
				"label": "",
				"isSensor": false,
				"vertices": [
					[ { "x":187, "y":0 }, { "x":180, "y":18 }, { "x":219, "y":31 } ],
					[ { "x":180, "y":18 }, { "x":152, "y":48 }, { "x":257, "y":48 }, { "x":219, "y":31 } ],
					[ { "x":152, "y":48 }, { "x":105, "y":82 }, { "x":21, "y":261 }, { "x":40, "y":281 }, { "x":72, "y":300 }, { "x":257, "y":48 } ],
					[ { "x":385, "y":42 }, { "x":346, "y":41 }, { "x":293, "y":52 }, { "x":515, "y":180 }, { "x":454, "y":94 }, { "x":418, "y":58 } ],
					[ { "x":135, "y":757 }, { "x":180, "y":796 }, { "x":247, "y":827 }, { "x":356, "y":861 }, { "x":512, "y":898 }, { "x":142, "y":513 }, { "x":116, "y":671 }, { "x":119, "y":718 } ],
					[ { "x":846, "y":75 }, { "x":821, "y":80 }, { "x":807, "y":91 }, { "x":797, "y":107 }, { "x":786, "y":141 }, { "x":764, "y":262 }, { "x":1022, "y":160 }, { "x":883, "y":86 } ],
					[ { "x":0, "y":191 }, { "x":5, "y":228 }, { "x":21, "y":261 }, { "x":105, "y":82 }, { "x":48, "y":115 }, { "x":23, "y":138 }, { "x":9, "y":159 } ],
					[ { "x":764, "y":262 }, { "x":745, "y":330 }, { "x":1078, "y":182 }, { "x":1022, "y":160 } ],
					[ { "x":512, "y":898 }, { "x":648, "y":909 }, { "x":754, "y":903 }, { "x":848, "y":890 }, { "x":935, "y":871 }, { "x":1019, "y":846 }, { "x":652, "y":388 }, { "x":142, "y":513 } ],
					[ { "x":1342, "y":261 }, { "x":1321, "y":238 }, { "x":1269, "y":714 }, { "x":1303, "y":680 }, { "x":1346, "y":601 }, { "x":1370, "y":408 }, { "x":1370, "y":353 }, { "x":1361, "y":304 } ],
					[ { "x":1331, "y":640 }, { "x":1346, "y":601 }, { "x":1303, "y":680 } ],
					[ { "x":515, "y":180 }, { "x":293, "y":52 }, { "x":257, "y":48 }, { "x":119, "y":364 }, { "x":134, "y":408 }, { "x":652, "y":388 }, { "x":580, "y":261 } ],
					[ { "x":745, "y":330 }, { "x":718, "y":388 }, { "x":1144, "y":197 }, { "x":1078, "y":182 } ],
					[ { "x":72, "y":300 }, { "x":95, "y":323 }, { "x":257, "y":48 } ],
					[ { "x":95, "y":323 }, { "x":119, "y":364 }, { "x":257, "y":48 } ],
					[ { "x":1244, "y":205 }, { "x":1144, "y":197 }, { "x":718, "y":388 }, { "x":706, "y":401 }, { "x":1097, "y":816 }, { "x":1321, "y":238 }, { "x":1300, "y":224 } ],
					[ { "x":134, "y":408 }, { "x":143, "y":470 }, { "x":652, "y":388 } ],
					[ { "x":143, "y":470 }, { "x":142, "y":513 }, { "x":652, "y":388 } ],
					[ { "x":1019, "y":846 }, { "x":1097, "y":816 }, { "x":671, "y":404 }, { "x":652, "y":388 } ],
					[ { "x":1269, "y":714 }, { "x":1321, "y":238 }, { "x":1097, "y":816 }, { "x":1171, "y":780 }, { "x":1232, "y":743 } ],
					[ { "x":706, "y":401 }, { "x":689, "y":409 }, { "x":1097, "y":816 } ],
					[ { "x":689, "y":409 }, { "x":671, "y":404 }, { "x":1097, "y":816 } ]
				]
			}
		]
	}
}
